trame_jupyter_extension/__init__.py
trame_jupyter_extension/_version.py
trame_jupyter_extension/handlers.py
trame_jupyter_extension-2.1.3.data/data/etc/jupyter/jupyter_server_config.d/trame_jupyter_extension.json
trame_jupyter_extension-2.1.3.data/data/share/jupyter/labextensions/trame-jupyter-extension/package.json
trame_jupyter_extension-2.1.3.data/data/share/jupyter/labextensions/trame-jupyter-extension/static/612.f7d795133c6cf3376662.js
trame_jupyter_extension-2.1.3.data/data/share/jupyter/labextensions/trame-jupyter-extension/static/728.c59280d1c518b42b0977.js
trame_jupyter_extension-2.1.3.data/data/share/jupyter/labextensions/trame-jupyter-extension/static/remoteEntry.94249a0cd34232308aac.js
trame_jupyter_extension-2.1.3.data/data/share/jupyter/labextensions/trame-jupyter-extension/static/style.js
trame_jupyter_extension-2.1.3.data/data/share/jupyter/labextensions/trame-jupyter-extension/static/third-party-licenses.json
trame_jupyter_extension-2.1.3.data/data/share/jupyter/labextensions/trame-jupyter-extension/install.json
trame_jupyter_extension-2.1.3.dist-info/METADATA
trame_jupyter_extension-2.1.3.dist-info/WHEEL
trame_jupyter_extension-2.1.3.dist-info/licenses/LICENSE
trame_jupyter_extension-2.1.3.dist-info/RECORD
