Metadata-Version: 2.3
Name: trame-jupyter-extension
Version: 2.1.3
Dynamic: Keywords
Summary: A JupyterLab extension for trame communication layer
Project-URL: Homepage, https://github.com/Kitware/trame-jupyter-extension
Project-URL: Bug Tracker, https://github.com/Kitware/trame-jupyter-extension/issues
Project-URL: Repository, https://github.com/Kitware/trame-jupyter-extension.git
Author-email: "Kitware Inc." <sebastien.jourdain@kitware.com>
License: BSD 3-Clause License
License-File: LICENSE
Classifier: Framework :: Jupyter
Classifier: Framework :: Jupyter :: JupyterLab
Classifier: Framework :: Jupyter :: JupyterLab :: 4
Classifier: Framework :: Jupyter :: JupyterLab :: Extensions
Classifier: Framework :: Jupyter :: JupyterLab :: Extensions :: Prebuilt
Classifier: License :: OSI Approved :: BSD License
Classifier: Programming Language :: Python
Classifier: Programming Language :: Python :: 3
Classifier: Programming Language :: Python :: 3.8
Classifier: Programming Language :: Python :: 3.9
Classifier: Programming Language :: Python :: 3.10
Classifier: Programming Language :: Python :: 3.11
Requires-Python: >=3.8
Requires-Dist: jupyter-server<3,>=2.0.1
Requires-Dist: jupyterlab<5,>=4
Requires-Dist: trame>=3.2.7
